odoo/addons/account_invoice_report_payment_info/README.rst
odoo/addons/account_invoice_report_payment_info/__init__.py
odoo/addons/account_invoice_report_payment_info/__manifest__.py
odoo/addons/account_invoice_report_payment_info/data/payment_info_data.xml
odoo/addons/account_invoice_report_payment_info/i18n/account_invoice_report_payment_info.pot
odoo/addons/account_invoice_report_payment_info/i18n/es.po
odoo/addons/account_invoice_report_payment_info/i18n/it.po
odoo/addons/account_invoice_report_payment_info/i18n/pt_BR.po
odoo/addons/account_invoice_report_payment_info/models/__init__.py
odoo/addons/account_invoice_report_payment_info/models/account_invoice.py
odoo/addons/account_invoice_report_payment_info/readme/CONFIGURE.md
odoo/addons/account_invoice_report_payment_info/readme/CONTRIBUTORS.md
odoo/addons/account_invoice_report_payment_info/readme/DESCRIPTION.md
odoo/addons/account_invoice_report_payment_info/readme/USAGE.md
odoo/addons/account_invoice_report_payment_info/static/description/icon.png
odoo/addons/account_invoice_report_payment_info/static/description/index.html
odoo/addons/account_invoice_report_payment_info/views/report_invoice.xml
odoo_addon_account_invoice_report_payment_info-18.0.1.0.0.3.dist-info/METADATA
odoo_addon_account_invoice_report_payment_info-18.0.1.0.0.3.dist-info/WHEEL
odoo_addon_account_invoice_report_payment_info-18.0.1.0.0.3.dist-info/top_level.txt
odoo_addon_account_invoice_report_payment_info-18.0.1.0.0.3.dist-info/RECORD
